{
    "name": "Swamp Dark Ossian",
    "type": "dark",
    "semanticHighlighting": true,
    "colors": {
        "button.background": "#3b3750ff",
        "button.foreground": "#fff1e8",
        "button.hoverBackground": "#bb99a9ff",
        "activityBar.background": "#1b0502ff",
        "activityBar.foreground": "#FFE2D7ff",
        "activityBar.inactiveForeground": "#feb79cff",
        "activityBarBadge.background": "#6dd3ceff",
        "activityBarBadge.foreground": "#1b0502ff",
        "sideBar.background": "#1b0502ff",
        "sideBar.foreground": "#FFE2D7ff",
        "sideBar.dropBackground": "#bb99a9ff",
        "sideBar.border": "#00000000",
        "sideBarTitle.foreground": "#feb79cff",
        "sideBarSectionHeader.background": "#1b0502ff",
        "sideBarSectionHeader.foreground": "#feb79cff",
        "editorGroup.border": "#00000000",
        "editorGroup.dropBackground": "#3b375066",
        "editorGroupHeader.noTabsBackground": "#1B0502",
        "editorGroupHeader.tabsBackground": "#1B0502",
        "editorGroupHeader.tabsBorder": "#ff000000",
        "editorGroup.emptyBackground": "#5f574f00",
        "editorGroup.focusedEmptyBorder": "#c2c3c700",
        "tab.activeBackground": "#feb79cff",
        "tab.activeForeground": "#1b0502ff",
        "tab.border": "#ff004d00",
        "tab.inactiveBackground": "#130402",
        "tab.inactiveForeground": "#cc9483ff",
        "editorPane.background": "#000",
        "editor.background": "#130402",
        "editor.foreground": "#bb99a9ff",
        "editorLineNumber.foreground": "#705B39",
        "editorLineNumber.activeForeground": "#ab8418ff",
        "editorCursor.foreground": "#c8e9a0ff",
        "editor.selectionBackground": "#3b3750ff",
        "editor.lineHighlightBorder": "#ff000000",
        "editorWidget.background": "#3b3750ff",
        "editorWidget.border": "#000000",
        "peekViewEditor.background": "#3b3750ff",
        "panel.background": "#1b0502ff",
        "panel.border": "#bb99a9ff",
        "titleBar.activeBackground": "#3b3750ff",
        "statusBar.background": "#cc9483ff",
        "statusBar.foreground": "#1b0502ff"
    },
    "semanticTokenColors": {
        "variable.readonly": "#6dd3ceff",
        "namespace": {
            "fontStyle": "italic",
            "foreground": "#a8d0dbff"
        },
        "function": "#feb79cff",
        "function.declaration": "#feb79cff",
        "parameter": {
            "fontStyle": "",
            "foreground": "#cc9483ff"
        },
        "property": {
            "fontStyle": "italic",
            "foreground": "#bb99a9ff"
        },
        "number": "#FFE2D7",
        "enum": "#feb79cff",
        "enumMember": "#cc9483ff",
        "class": "#ad8f4c",
        "keyword": "#bb99a9ff",
        "string": {
            "foreground": "#FFE2D7",
            "fontStyle": "italic"
        },
        "macro": "#feb79cff",
        "type": "#cc9483ff",
        "typeParameter": "#78f0e8",
        "typeParameter.declaration": "#e5faf5",
        "type.declaration": "#ab8418ff",
        "type.declaration.defaultLibrary": "#705b39ff",
        "comment": "#6dd3ceff",
        "punctuation": "#3b3750ff",
        "operator": "#3b3750ff"
    }
}